easyprov/__init__.py
easyprov/direnv.py
easyprov/explore.py
easyprov/prov_csv.py
easyprov/prov_json.py
easyprov/prov_mpl.py
easyprov/prov_rst.py
easyprov/provenance.py
easyprov/version.py
easyprov-1.1.0.dist-info/licenses/AUTHORS.rst
easyprov-1.1.0.dist-info/licenses/LICENSE
easyprov-1.1.0.dist-info/METADATA
easyprov-1.1.0.dist-info/WHEEL
easyprov-1.1.0.dist-info/top_level.txt
easyprov-1.1.0.dist-info/RECORD
