Metadata-Version: 2.4
Name: easyprov
Version: 1.1.0
Summary: Simply store provenance in data produced by python scripts
Author-email: revesansparole <revesansparole@gmail.com>
Maintainer-email: revesansparole <revesansparole@gmail.com>, Jerome Chopard <revesansparole@gmail.com>
License: cc_by_nc
Project-URL: repository, https://gitlab.com/revesansparole/easyprov
Project-URL: pip, https://pypi.org/project/easyprov/1.1.0/
Project-URL: conda, https://anaconda.org/revesansparole/easyprov
Project-URL: doc, https://revesansparole.gitlab.io/easyprov/
Project-URL: pypi, https://badge.fury.io/py/easyprov
Classifier: Development Status :: 2 - Pre-Alpha
Classifier: Intended Audience :: Developers
Classifier: License :: OSI Approved :: BSD License
Classifier: Natural Language :: English
Classifier: Programming Language :: Python
Classifier: Programming Language :: Python :: 3
Classifier: Programming Language :: Python :: 3 :: Only
Classifier: Programming Language :: Python :: 3.10
Classifier: Programming Language :: Python :: 3.11
Requires-Python: >=3.10
License-File: LICENSE
License-File: AUTHORS.rst
Provides-Extra: doc
Requires-Dist: sphinx; extra == "doc"
Requires-Dist: sphinx-gallery; extra == "doc"
Requires-Dist: sphinx-rtd-theme; extra == "doc"
Provides-Extra: dvlpt
Requires-Dist: black; extra == "dvlpt"
Requires-Dist: twine; extra == "dvlpt"
Provides-Extra: example
Requires-Dist: matplotlib; extra == "example"
Requires-Dist: pandas; extra == "example"
Provides-Extra: test
Requires-Dist: coverage; extra == "test"
Requires-Dist: matplotlib; extra == "test"
Requires-Dist: pandas; extra == "test"
Requires-Dist: pytest; extra == "test"
Requires-Dist: pytest-cov; extra == "test"
Requires-Dist: pytest-mock; extra == "test"
Dynamic: license-file
